{
    "swww": {
        "cargoLocks": null,
        "date": "2024-03-23",
        "extract": null,
        "name": "swww",
        "passthru": null,
        "pinned": false,
        "src": {
            "deepClone": false,
            "fetchSubmodules": false,
            "leaveDotGit": false,
            "name": null,
            "owner": "LGFae",
            "repo": "swww",
            "rev": "dcf0d4e481b13c19f2490d730cb45c03d4e8b77b",
            "sha256": "sha256-HfK9AOTsTO0JnrD6e6g/LtwukOjDhf9ZeC6/TmNZqDc=",
            "type": "github"
        },
        "version": "dcf0d4e481b13c19f2490d730cb45c03d4e8b77b"
    },
    "transmission-web-soft-theme": {
        "cargoLocks": null,
        "date": "2021-01-28",
        "extract": null,
        "name": "transmission-web-soft-theme",
        "passthru": null,
        "pinned": false,
        "src": {
            "deepClone": false,
            "fetchSubmodules": false,
            "leaveDotGit": false,
            "name": null,
            "owner": "diesys",
            "repo": "transmission-web-soft-theme",
            "rev": "a957b41b0303e6b74e67191311e0d2af9b60a965",
            "sha256": "sha256-KngN44lnhv0sga0otYC9F5xoqLDDIVxobXRlhhhSmHo=",
            "type": "github"
        },
        "version": "a957b41b0303e6b74e67191311e0d2af9b60a965"
    },
    "wallust": {
        "cargoLocks": null,
        "date": "2024-03-08",
        "extract": null,
        "name": "wallust",
        "passthru": null,
        "pinned": false,
        "src": {
            "deepClone": false,
            "fetchSubmodules": false,
            "leaveDotGit": false,
            "name": null,
            "rev": "104d99fcb4ada743d45de76caa48cd899b021601",
            "sha256": "sha256-gGyxRdv2I/3TQWrTbUjlJGsaRv4SaNE+4Zo9LMWmxk8=",
            "type": "git",
            "url": "https://codeberg.org/explosion-mental/wallust.git"
        },
        "version": "104d99fcb4ada743d45de76caa48cd899b021601"
    },
    "waybar": {
        "cargoLocks": null,
        "date": "2024-03-24",
        "extract": null,
        "name": "waybar",
        "passthru": null,
        "pinned": false,
        "src": {
            "deepClone": false,
            "fetchSubmodules": false,
            "leaveDotGit": false,
            "name": null,
            "owner": "Alexays",
            "repo": "Waybar",
            "rev": "487ab2325996b922b5f62e1930040b6d71bfd39f",
            "sha256": "sha256-xxGx5ortDMIQIdVAYn/vtakiLjNdgNKUNkUc8b5wBbc=",
            "type": "github"
        },
        "version": "487ab2325996b922b5f62e1930040b6d71bfd39f"
    },
    "wezterm": {
        "cargoLocks": null,
        "date": "2024-03-16",
        "extract": null,
        "name": "wezterm",
        "passthru": null,
        "pinned": false,
        "src": {
            "deepClone": false,
            "fetchSubmodules": true,
            "leaveDotGit": false,
            "name": null,
            "owner": "wez",
            "repo": "wezterm",
            "rev": "889f8a9cd71a2b3552f28f6d1864aa3cd9461fdf",
            "sha256": "sha256-H8c7oSJufX2AEgcBk7eMrlFw+x0SgI9vI4iKlNojvMk=",
            "type": "github"
        },
        "version": "889f8a9cd71a2b3552f28f6d1864aa3cd9461fdf"
    }
}